hp_money/__init__.py
hp_money/amount/__init__.py
hp_money/currency/__init__.py
hp_money/fee_rate/__init__.py
hp_money/forex_rate/__init__.py
tests/__init__.py
tests/test_fee_rate.py
tests/test_forex_rate.py
tests/test_money.py
hp_money-1.1.2.dist-info/METADATA
hp_money-1.1.2.dist-info/WHEEL
hp_money-1.1.2.dist-info/top_level.txt
hp_money-1.1.2.dist-info/RECORD
