Metadata-Version: 2.1
Name: hp-money
Version: 1.1.2
Summary: money module of hipopay, including amount and currency sub-modules
Home-page: https://hipopay.com
Author: Qingxu Kuang
Author-email: kuangqingxu@transfereasy.com
License: UNKNOWN
Platform: UNKNOWN
Classifier: Programming Language :: Python :: 3.8
Requires-Python: >=3.8
